{"trades":[{"price":70.89,"symbol":"쫦쿘≷"},{"price":28.86,"symbol":"헌刌ࢴ"},{"price":38.92,"symbol":"ᷗひ岝"},{"price":80.6,"symbol":"ὭΙፖⲘ"},{"price":41.47,"symbol":"䦸ʯ欣"},{"price":68.7,"symbol":"⿓Մ썒"},{"price":38.05,"symbol":"ሗ㫔㦢"},{"price":22.46,"symbol":"ە贆⚝"},{"price":74.52,"symbol":"禈랪馴"},{"price":55.08,"symbol":"爞Ӟ顷"},{"price":78.13,"symbol":"쭀걭唳"},{"price":84.01,"symbol":"쌯㑥⟙"},{"price":72.06,"symbol":"╮嘻两"},{"price":40.45,"symbol":"冥줡갴"},{"price":96.82,"symbol":"㽚萠Ꚛ"},{"price":16.81,"symbol":"캨ꀽ섣"},{"price":25.2,"symbol":"㿜꺚鱚"},{"price":11.52,"symbol":"䏅콠恻"},{"price":29.52,"symbol":"∎튱鷈"}]}